dyscord/__init__.py
dyscord/version.py
dyscord/client/__init__.py
dyscord/client/discord_client.py
dyscord/client/enumerations.py
dyscord/client/events.py
dyscord/client/api/__init__.py
dyscord/client/api/api_v9.py
dyscord/command/__init__.py
dyscord/helper/__init__.py
dyscord/helper/auth_loop.py
dyscord/helper/command_handler.py
dyscord/helper/interactions.py
dyscord/objects/__init__.py
dyscord/objects/activity.py
dyscord/objects/base_object.py
dyscord/objects/channel.py
dyscord/objects/embed.py
dyscord/objects/emoji.py
dyscord/objects/enumerations.py
dyscord/objects/guild.py
dyscord/objects/message.py
dyscord/objects/permissions.py
dyscord/objects/presence.py
dyscord/objects/ready.py
dyscord/objects/role.py
dyscord/objects/snowflake.py
dyscord/objects/user.py
dyscord/objects/events/__init__.py
dyscord/objects/events/guild_member_update.py
dyscord/objects/events/typing_start.py
dyscord/objects/events/voice_state.py
dyscord/objects/interactions/__init__.py
dyscord/objects/interactions/command.py
dyscord/objects/interactions/components.py
dyscord/objects/interactions/enumerations.py
dyscord/objects/interactions/interaction.py
dyscord/utilities/__init__.py
dyscord/utilities/borg.py
dyscord/utilities/cache.py
dyscord/utilities/log.py
dyscord-0.6.1.dist-info/LICENSE
dyscord-0.6.1.dist-info/METADATA
dyscord-0.6.1.dist-info/WHEEL
dyscord-0.6.1.dist-info/top_level.txt
dyscord-0.6.1.dist-info/RECORD
