Metadata-Version: 2.1
Name: dyscord
Version: 0.6.1
Summary: A simple implementation of the discord API.
Home-page: https://github.com/isbe-house/dyscord
Author: John Murray
Author-email: jmurrayufo@gmail.com
License: GPLv3
Project-URL: Bug Tracker, https://github.com/isbe-house/dyscord/issues
Platform: any
Classifier: Development Status :: 3 - Alpha
Classifier: Framework :: Pytest
Classifier: Intended Audience :: Developers
Classifier: License :: OSI Approved :: GNU General Public License v3 (GPLv3)
Classifier: Natural Language :: English
Classifier: Operating System :: OS Independent
Classifier: Programming Language :: Python :: 3.10
Classifier: Programming Language :: Python :: 3.8
Classifier: Programming Language :: Python :: 3.9
Classifier: Topic :: Communications :: Chat
Requires-Python: >=3.8
License-File: LICENSE
Requires-Dist: cachetools (>=4.2.4)
Requires-Dist: colour (>=0.1.5)
Requires-Dist: emoji (>=1.5.0)
Requires-Dist: httpx (>=0.19.0)
Requires-Dist: nest-asyncio (>=1.5.1)
Requires-Dist: orjson (>=3.6.3)
Requires-Dist: requests (>=2.26.0)
Requires-Dist: websockets (>=10.0)
Requires-Dist: validators (>=0.18.2)
Requires-Dist: logging-levels (>=0.3.0)
